mediacatch/__init__.py
mediacatch/assets/Arial.ttf
mediacatch/commands/__init__.py
mediacatch/commands/cli.py
mediacatch/commands/embed.py
mediacatch/commands/speech.py
mediacatch/commands/vision.py
mediacatch/commands/viz.py
mediacatch/speech/__init__.py
mediacatch/speech/embed.py
mediacatch/speech/result.py
mediacatch/speech/upload.py
mediacatch/utils/__init__.py
mediacatch/utils/exceptions.py
mediacatch/utils/general.py
mediacatch/vision/__init__.py
mediacatch/vision/result.py
mediacatch/vision/upload.py
mediacatch/viz/__init__.py
mediacatch/viz/annotator.py
mediacatch/viz/base_viz.py
mediacatch/viz/detect.py
mediacatch/viz/face.py
mediacatch/viz/ocr.py
mediacatch/viz/speech.py
mediacatch-0.5.1.dist-info/METADATA
mediacatch-0.5.1.dist-info/WHEEL
mediacatch-0.5.1.dist-info/entry_points.txt
mediacatch-0.5.1.dist-info/RECORD
