Metadata-Version: 2.4
Name: mediacatch
Version: 0.5.1
Summary: Python package for easily interfacing with MediaCatch APIs and data formats.
Project-URL: Documentation, https://api.mediacatch.io/mediacatch/docs/
Author-email: Mathias Nielsen <mathias@mediacatch.io>
License-Expression: MIT
Classifier: Framework :: FastAPI
Classifier: Intended Audience :: Developers
Classifier: License :: OSI Approved :: MIT License
Classifier: Programming Language :: Python :: 3 :: Only
Classifier: Programming Language :: Python :: 3.10
Classifier: Topic :: Internet
Classifier: Topic :: Software Development
Classifier: Topic :: Software Development :: Libraries
Classifier: Topic :: Software Development :: Libraries :: Application Frameworks
Classifier: Topic :: Software Development :: Libraries :: Python Modules
Requires-Python: >=3.10
Requires-Dist: numpy<3.0.0,>=1.26.4
Requires-Dist: opencv-python-headless<5.0.0,>=4.11.0
Requires-Dist: pillow<12.0.0,>=11.1.0
Requires-Dist: pydantic<3.0.0,>=2.11.7
Requires-Dist: python-dotenv<2.0.0,>=1.0.0
Requires-Dist: requests<3.0.0,>=2.32.3
Requires-Dist: srt<4.0.0,>=3.5.3
Requires-Dist: tqdm<5.0.0,>=4.67.0
Requires-Dist: urllib3<3.0.0,>=2.2.3
